[
{"season": ["17-18"], "tm": ["波特兰开拓者"], "g": ["73"], "gs": ["73"], "mp": ["36.6"], "fgper": ["43.9%"], "fg": ["8.5"], "fga": ["19.4"], "threepper": ["36.1%"], "threep": ["3.1"], "threepa": ["8.6"], "ftper": ["91.6%"], "ft": ["6.8"], "fta": ["7.4"], "trb": ["4.5"], "orb": ["0.8"], "drb": ["3.6"], "ast": ["6.6"], "stl": ["1.1"], "blk": ["0.4"], "tov": ["2.8"], "pf": ["1.6"], "pts": ["26.9"], "w": ["44"], "l": ["29"]},
{"season": ["16-17"], "tm": ["波特兰开拓者"], "g": ["75"], "gs": ["75"], "mp": ["35.9"], "fgper": ["44.4%"], "fg": ["8.8"], "fga": ["19.8"], "threepper": ["37.0%"], "threep": ["2.9"], "threepa": ["7.7"], "ftper": ["89.5%"], "ft": ["6.5"], "fta": ["7.3"], "trb": ["4.9"], "orb": ["0.6"], "drb": ["4.3"], "ast": ["5.9"], "stl": ["0.9"], "blk": ["0.3"], "tov": ["2.6"], "pf": ["2.0"], "pts": ["27.0"], "w": ["38"], "l": ["37"]},
{"season": ["15-16"], "tm": ["波特兰开拓者"], "g": ["75"], "gs": ["75"], "mp": ["35.6"], "fgper": ["41.9%"], "fg": ["8.2"], "fga": ["19.7"], "threepper": ["37.5%"], "threep": ["3.1"], "threepa": ["8.1"], "ftper": ["89.2%"], "ft": ["5.5"], "fta": ["6.2"], "trb": ["4.0"], "orb": ["0.6"], "drb": ["3.4"], "ast": ["6.8"], "stl": ["0.9"], "blk": ["0.4"], "tov": ["3.2"], "pf": ["2.2"], "pts": ["25.1"], "w": ["40"], "l": ["35"]},
{"season": ["14-15"], "tm": ["波特兰开拓者"], "g": ["82"], "gs": ["82"], "mp": ["35.7"], "fgper": ["43.4%"], "fg": ["7.2"], "fga": ["16.6"], "threepper": ["34.3%"], "threep": ["2.4"], "threepa": ["7.0"], "ftper": ["86.4%"], "ft": ["4.2"], "fta": ["4.9"], "trb": ["4.6"], "orb": ["0.6"], "drb": ["4.0"], "ast": ["6.2"], "stl": ["1.2"], "blk": ["0.3"], "tov": ["2.7"], "pf": ["2.0"], "pts": ["21.0"], "w": ["51"], "l": ["31"]},
{"season": ["13-14"], "tm": ["波特兰开拓者"], "g": ["82"], "gs": ["82"], "mp": ["35.8"], "fgper": ["42.4%"], "fg": ["6.7"], "fga": ["15.9"], "threepper": ["39.4%"], "threep": ["2.7"], "threepa": ["6.8"], "ftper": ["87.1%"], "ft": ["4.5"], "fta": ["5.2"], "trb": ["3.5"], "orb": ["0.4"], "drb": ["3.1"], "ast": ["5.6"], "stl": ["0.8"], "blk": ["0.3"], "tov": ["2.4"], "pf": ["2.4"], "pts": ["20.7"], "w": ["54"], "l": ["28"]},
{"season": ["12-13"], "tm": ["波特兰开拓者"], "g": ["82"], "gs": ["82"], "mp": ["38.6"], "fgper": ["42.9%"], "fg": ["6.7"], "fga": ["15.7"], "threepper": ["36.8%"], "threep": ["2.3"], "threepa": ["6.1"], "ftper": ["84.4%"], "ft": ["3.3"], "fta": ["3.9"], "trb": ["3.1"], "orb": ["0.5"], "drb": ["2.6"], "ast": ["6.5"], "stl": ["0.9"], "blk": ["0.2"], "tov": ["3.0"], "pf": ["2.1"], "pts": ["19.0"], "w": ["33"], "l": ["49"]}
]